[
  {
    "type": "DATA_QUALITY_ALERT",
    "timestamp": "2025-06-10T23:07:14.156749",
    "source": "test_source",
    "quality_score": 0.5499999999999999,
    "issues": [
      "High null percentage: 50.0%",
      "Missing fields: ['symbol', 'volume', 'open_interest']"
    ],
    "severity": "HIGH"
  },
  {
    "type": "DATA_QUALITY_ALERT",
    "timestamp": "2025-06-10T23:10:54.450655",
    "source": "test_source",
    "quality_score": 0.5499999999999999,
    "issues": [
      "High null percentage: 50.0%",
      "Missing fields: ['symbol', 'volume', 'open_interest']"
    ],
    "severity": "HIGH"
  }
]